[{"id":"3ef320e8.d9476","type":"tab","label":"Flow 1","disabled":false,"info":""},{"id":"9f1683d.72d5c8","type":"debug","z":"3ef320e8.d9476","name":"","active":true,"tosidebar":true,"console":false,"tostatus":false,"complete":"false","x":1170,"y":580,"wires":[]},{"id":"cc255028.18d47","type":"ibmiot in","z":"3ef320e8.d9476","authentication":"apiKey","apiKey":"212d946.d4fc46c","inputType":"evt","logicalInterface":"","ruleId":"","deviceId":"","applicationId":"","deviceType":"+","eventType":"+","commandType":"","format":"json","name":"IBM IoT","service":"registered","allDevices":"","allApplications":"","allDeviceTypes":true,"allLogicalInterfaces":"","allEvents":true,"allCommands":"","allFormats":"","qos":0,"x":70,"y":120,"wires":[["dd5b154b.a95938","32e6f79e.64d1e8","b7dc0cb1.0b575"]]},{"id":"dd5b154b.a95938","type":"function","z":"3ef320e8.d9476","name":"temp","func":"msg.payload=msg.payload.d.temperature\nreturn msg;","outputs":1,"noerr":0,"x":270,"y":60,"wires":[["dcb7e719.363008","b810ccd5.b1181"]]},{"id":"32e6f79e.64d1e8","type":"function","z":"3ef320e8.d9476","name":"humidity","func":"msg.payload=msg.payload.d.humidity\nreturn msg;","outputs":1,"noerr":0,"x":260,"y":160,"wires":[["56d68451.be258c","1b5b6c0c.1ce204"]]},{"id":"b7dc0cb1.0b575","type":"function","z":"3ef320e8.d9476","name":"Moisture","func":"msg.payload=msg.payload.d.objectTemp\nreturn msg;","outputs":1,"noerr":0,"x":260,"y":260,"wires":[["b8ee83a2.6bd72","b48b4ec1.6d428"]]},{"id":"dcb7e719.363008","type":"ui_gauge","z":"3ef320e8.d9476","name":"","group":"1df4fd44.c27b23","order":0,"width":0,"height":0,"gtype":"gage","title":"Temprature gauge","label":"c","format":"{{value}}","min":0,"max":"100","colors":["#0cb300","#e6e600","#ca3838"],"seg1":"40","seg2":"60","x":510,"y":60,"wires":[]},{"id":"b8ee83a2.6bd72","type":"ui_gauge","z":"3ef320e8.d9476","name":"Moisture gauge","group":"a646aa96.a6cb48","order":1,"width":"6","height":"4","gtype":"gage","title":"Moisture gauge","label":"%","format":"{{value}}","min":0,"max":"100","colors":["#00b500","#e6e600","#ca3838"],"seg1":"","seg2":"","x":560,"y":260,"wires":[],"inputLabels":["hi"],"icon":"font-awesome/fa-eur"},{"id":"56d68451.be258c","type":"ui_gauge","z":"3ef320e8.d9476","name":"","group":"4aac1316.5136ec","order":0,"width":"6","height":"4","gtype":"gage","title":"Humidity gauge","label":"%","format":"{{value}}","min":0,"max":"100","colors":["#00b500","#e6e600","#ca3838"],"seg1":"40","seg2":"70","x":540,"y":160,"wires":[]},{"id":"7762dd94.c2bcb4","type":"ibmiot out","z":"3ef320e8.d9476","authentication":"apiKey","apiKey":"212d946.d4fc46c","outputType":"cmd","deviceId":"123456","deviceType":"node","eventCommandType":"home","format":"json","data":"data","qos":0,"name":"IBM IoT","service":"registered","x":1180,"y":520,"wires":[]},{"id":"e7122f4d.acf08","type":"ui_toast","z":"3ef320e8.d9476","position":"dialog","displayTime":"3","highlight":"","sendall":true,"outputs":1,"ok":"OK","cancel":"","raw":true,"topic":" STATUS","name":"ON","x":810,"y":520,"wires":[[]]},{"id":"b810ccd5.b1181","type":"ui_chart","z":"3ef320e8.d9476","name":"TEMPRATURE","group":"b4d5ddbf.fcfb3","order":4,"width":0,"height":0,"label":"","chartType":"line","legend":"false","xformat":"HH:mm","interpolate":"linear","nodata":"","dot":false,"ymin":"0","ymax":"100","removeOlder":1,"removeOlderPoints":"","removeOlderUnit":"60","cutout":0,"useOneColor":false,"useUTC":false,"colors":["#f9c610","#aec7e8","#fdbe12","#2ca02c","#98df8a","#d62728","#ff9896","#9467bd","#c5b0d5"],"useOldStyle":false,"outputs":1,"x":740,"y":60,"wires":[["f83eb1a.e15475"]]},{"id":"f883ffd6.6fe67","type":"ui_switch","z":"3ef320e8.d9476","name":"","label":"MOTOR SWITCH","tooltip":"","group":"95844504.a842f8","order":5,"width":0,"height":0,"passthru":false,"decouple":"false","topic":"","style":"","onvalue":"{\"command\":\"motor on\"}","onvalueType":"str","onicon":"fa-toggle-on","oncolor":"Green","offvalue":"{\"command\":\"motor off\"}","offvalueType":"str","officon":"fa-toggle-off","offcolor":"red","x":110,"y":580,"wires":[["7762dd94.c2bcb4","9f1683d.72d5c8","5cc89c5a.e84824"]]},{"id":"f8bb5041.82de5","type":"ui_toast","z":"3ef320e8.d9476","position":"dialog","displayTime":"5","highlight":"","sendall":true,"outputs":1,"ok":"OK","cancel":"","raw":true,"topic":" STATUS","name":"","x":830,"y":680,"wires":[[]]},{"id":"b48b4ec1.6d428","type":"ui_chart","z":"3ef320e8.d9476","name":"Moisture","group":"6ca04aa4.b16754","order":4,"width":0,"height":0,"label":"","chartType":"line","legend":"false","xformat":"HH:mm","interpolate":"linear","nodata":"","dot":false,"ymin":"0","ymax":"100","removeOlder":1,"removeOlderPoints":"","removeOlderUnit":"60","cutout":0,"useOneColor":false,"useUTC":false,"colors":["#f9c610","#aec7e8","#fdbe12","#2ca02c","#98df8a","#d62728","#ff9896","#9467bd","#c5b0d5"],"useOldStyle":false,"outputs":1,"x":780,"y":260,"wires":[["f83eb1a.e15475"]]},{"id":"1b5b6c0c.1ce204","type":"ui_chart","z":"3ef320e8.d9476","name":"Humidity","group":"d2649f62.39199","order":4,"width":"6","height":"4","label":"","chartType":"line","legend":"false","xformat":"HH:mm","interpolate":"linear","nodata":"","dot":false,"ymin":"0","ymax":"100","removeOlder":1,"removeOlderPoints":"","removeOlderUnit":"60","cutout":0,"useOneColor":false,"useUTC":false,"colors":["#f9c610","#aec7e8","#fdbe12","#2ca02c","#98df8a","#d62728","#ff9896","#9467bd","#c5b0d5"],"useOldStyle":false,"outputs":1,"x":760,"y":160,"wires":[["f83eb1a.e15475"]]},{"id":"e4904fd0.66713","type":"http request","z":"3ef320e8.d9476","name":"WEATHER","method":"GET","ret":"obj","paytoqs":false,"url":"http://api.openweathermap.org/data/2.5/weather?q=Chennai,%20IN&appid=98048174abb95367f6968410c3208a14","tls":"","persist":false,"proxy":"","authType":"","x":290,"y":860,"wires":[["7506b8f6.5589b8","6d38bdd5.2f8954","764a4d6.7ef31b4","5054e438.e9973c"]]},{"id":"9cca466f.5b7308","type":"debug","z":"3ef320e8.d9476","name":"","active":true,"tosidebar":true,"console":false,"tostatus":false,"complete":"payload","targetType":"msg","x":1170,"y":820,"wires":[]},{"id":"f7763d21.3def6","type":"inject","z":"3ef320e8.d9476","name":"","topic":"","payload":"","payloadType":"date","repeat":"","crontab":"","once":true,"onceDelay":"60","x":130,"y":860,"wires":[["e4904fd0.66713"]]},{"id":"7506b8f6.5589b8","type":"function","z":"3ef320e8.d9476","name":"temp","func":"msg.payload=msg.payload.main.temp\nreturn msg;","outputs":1,"noerr":0,"x":470,"y":760,"wires":[["9cca466f.5b7308","50c87b6c.1e2bc4"]]},{"id":"764a4d6.7ef31b4","type":"function","z":"3ef320e8.d9476","name":"humidity","func":"msg.payload=msg.payload.main.humidity\nreturn msg;","outputs":1,"noerr":0,"x":480,"y":900,"wires":[["9cca466f.5b7308","b0177c05.d1c4d"]]},{"id":"6d38bdd5.2f8954","type":"function","z":"3ef320e8.d9476","name":"Pressure","func":"msg.payload=msg.payload.main.pressure\nreturn msg;","outputs":1,"noerr":0,"x":480,"y":840,"wires":[["9cca466f.5b7308","1bef47f7.447268"]]},{"id":"5054e438.e9973c","type":"function","z":"3ef320e8.d9476","name":"Weather","func":"msg.payload=msg.payload.weather[0].main\nreturn msg;","outputs":1,"noerr":0,"x":480,"y":960,"wires":[["9cca466f.5b7308","8862562b.451038"]]},{"id":"50c87b6c.1e2bc4","type":"ui_gauge","z":"3ef320e8.d9476","name":"","group":"952a132.5e838f","order":0,"width":0,"height":0,"gtype":"gage","title":"TEMPERATURE GAUGE","label":"C","format":"{{value}}","min":0,"max":"1000","colors":["#0cb300","#e6e600","#ca3838"],"seg1":"400","seg2":"500","x":870,"y":740,"wires":[]},{"id":"b0177c05.d1c4d","type":"ui_gauge","z":"3ef320e8.d9476","name":"","group":"64577732.9e8de8","order":0,"width":"6","height":"4","gtype":"donut","title":"HUMIDITY GAUGE","label":"%","format":"{{value}}","min":0,"max":"100","colors":["#00b500","#e6e600","#ca3838"],"seg1":"","seg2":"","x":830,"y":900,"wires":[]},{"id":"1bef47f7.447268","type":"ui_gauge","z":"3ef320e8.d9476","name":"Moisture gauge","group":"a387044d.fad078","order":1,"width":"6","height":"4","gtype":"gage","title":"PRESSURE GAUGE","label":"psi","format":"{{value}}","min":0,"max":"10000","colors":["#00b500","#e6e600","#ca3838"],"seg1":"","seg2":"","x":860,"y":820,"wires":[],"inputLabels":["hi"],"icon":"font-awesome/fa-eur"},{"id":"8862562b.451038","type":"ui_text","z":"3ef320e8.d9476","group":"c1531e07.38f2","order":1,"width":0,"height":0,"name":"","label":"CLIMATE","format":"{{msg.payload}}","layout":"row-spread","x":720,"y":960,"wires":[]},{"id":"5cc89c5a.e84824","type":"switch","z":"3ef320e8.d9476","name":"","property":"payload","propertyType":"msg","rules":[{"t":"eq","v":"{\"command\":\"motor on\"}","vt":"str"},{"t":"eq","v":"{\"command\":\"motor off\"}","vt":"str"}],"checkall":"false","repair":false,"outputs":2,"x":370,"y":600,"wires":[["164d76b6.82a879"],["1049b657.33e32a"]]},{"id":"1049b657.33e32a","type":"change","z":"3ef320e8.d9476","name":"","rules":[{"t":"set","p":"payload","pt":"msg","to":"MOTOR OFF","tot":"str"}],"action":"","property":"","from":"","to":"","reg":false,"x":400,"y":680,"wires":[["f8bb5041.82de5","cdf92743.8704f8"]]},{"id":"164d76b6.82a879","type":"change","z":"3ef320e8.d9476","name":"","rules":[{"t":"set","p":"payload","pt":"msg","to":"MOTOR ON","tot":"str"}],"action":"","property":"","from":"","to":"","reg":false,"x":380,"y":520,"wires":[["e7122f4d.acf08","413e3e06.a1463"]]},{"id":"413e3e06.a1463","type":"ui_audio","z":"3ef320e8.d9476","name":"","group":"95844504.a842f8","voice":"en-GB","always":"","x":640,"y":520,"wires":[]},{"id":"cdf92743.8704f8","type":"ui_audio","z":"3ef320e8.d9476","name":"","group":"95844504.a842f8","voice":"en-GB","always":"","x":660,"y":680,"wires":[]},{"id":"f83eb1a.e15475","type":"debug","z":"3ef320e8.d9476","name":"","active":true,"tosidebar":true,"console":false,"tostatus":false,"complete":"false","x":1150,"y":140,"wires":[]},{"id":"212d946.d4fc46c","type":"ibmiot","z":"","name":"IOT","keepalive":"60","serverName":"","cleansession":true,"appId":"","shared":false},{"id":"1df4fd44.c27b23","type":"ui_group","z":"","name":"Temperature ","tab":"121c4437.fdda0c","order":1,"disp":true,"width":"6","collapse":false},{"id":"a646aa96.a6cb48","type":"ui_group","z":"","name":"Moisture","tab":"121c4437.fdda0c","order":3,"disp":true,"width":"6","collapse":false},{"id":"4aac1316.5136ec","type":"ui_group","z":"","name":"Humidity","tab":"121c4437.fdda0c","order":2,"disp":true,"width":"6","collapse":false},{"id":"b4d5ddbf.fcfb3","type":"ui_group","z":"","name":"Temperature chart","tab":"121c4437.fdda0c","order":4,"disp":true,"width":"6","collapse":false},{"id":"95844504.a842f8","type":"ui_group","z":"","name":"Motor control","tab":"73130563.a4cc5c","order":2,"disp":true,"width":"6","collapse":false},{"id":"6ca04aa4.b16754","type":"ui_group","z":"","name":"Moisture chart","tab":"121c4437.fdda0c","order":6,"disp":true,"width":"6","collapse":false},{"id":"d2649f62.39199","type":"ui_group","z":"","name":"Humidity chart","tab":"121c4437.fdda0c","order":5,"disp":true,"width":"6","collapse":false},{"id":"952a132.5e838f","type":"ui_group","z":"","name":"TEMPERATURE","tab":"8a4190f6.6e941","order":1,"disp":true,"width":"6","collapse":false},{"id":"64577732.9e8de8","type":"ui_group","z":"","name":"HUMIDITY","tab":"8a4190f6.6e941","order":2,"disp":true,"width":"6","collapse":false},{"id":"a387044d.fad078","type":"ui_group","z":"","name":"PRESSURE","tab":"8a4190f6.6e941","order":3,"disp":true,"width":"6","collapse":false},{"id":"c1531e07.38f2","type":"ui_group","z":"","name":"CLIMATE","tab":"8a4190f6.6e941","order":4,"disp":true,"width":"6","collapse":false},{"id":"121c4437.fdda0c","type":"ui_tab","z":"","name":"Farm Data","icon":"dashboard","order":1,"disabled":false,"hidden":false},{"id":"73130563.a4cc5c","type":"ui_tab","z":"","name":"Motor Control","icon":"dashboard","order":3,"disabled":false,"hidden":false},{"id":"8a4190f6.6e941","type":"ui_tab","z":"","name":"Weather Data","icon":"dashboard","order":2,"disabled":false,"hidden":false}]